os_aio_pod/VERSION
os_aio_pod/__init__.py
os_aio_pod/bean.py
os_aio_pod/cmdline.py
os_aio_pod/config.py
os_aio_pod/decorators.py
os_aio_pod/initializers.py
os_aio_pod/main.py
os_aio_pod/pod.py
os_aio_pod/utils.py
os_aio_pod/commands/__init__.py
os_aio_pod/commands/run.py
os_aio_pod/contrib/__init__.py
os_aio_pod/contrib/aiohttp.py
os_aio_pod/contrib/aiomonitor.py
os_aio_pod/contrib/fromstdin.py
os_aio_pod/contrib/pcflow.py
os_aio_pod/contrib/ptpython.py
os_aio_pod/contrib/simple.py
os_aio_pod/contrib/tcp_server.py
os_aio_pod/contrib/uvicorn.py
os_aio_pod/examples/hello_world.py
os_aio_pod-0.1.40.dist-info/LICENSE
os_aio_pod-0.1.40.dist-info/METADATA
os_aio_pod-0.1.40.dist-info/WHEEL
os_aio_pod-0.1.40.dist-info/entry_points.txt
os_aio_pod-0.1.40.dist-info/top_level.txt
os_aio_pod-0.1.40.dist-info/RECORD
