Metadata-Version: 2.1
Name: os-aio-pod
Version: 0.1.40
Summary: A container of aio components.
Home-page: https://github.com/cfhamlet/os-aio-pod
Author: Ozzy
Author-email: cfhamlet@gmail.com
License: MIT License
Classifier: Development Status :: 2 - Pre-Alpha
Classifier: Intended Audience :: Developers
Classifier: License :: OSI Approved :: MIT License
Classifier: Natural Language :: English
Classifier: Programming Language :: Python :: 3
Classifier: Programming Language :: Python :: 3.6
Classifier: Programming Language :: Python :: 3.7
Classifier: Programming Language :: Python :: 3 :: Only
Classifier: Programming Language :: Python :: Implementation :: CPython
Requires-Python: >=3.6
License-File: LICENSE
Requires-Dist: click
Requires-Dist: pydantic (>=1.8)
Requires-Dist: asyncio-dispatch
Provides-Extra: aiohttp
Requires-Dist: aiohttp ; extra == 'aiohttp'
Provides-Extra: aiomonitor
Requires-Dist: aiomonitor ; extra == 'aiomonitor'
Provides-Extra: uvicorn
Requires-Dist: uvicorn ; extra == 'uvicorn'
Provides-Extra: uvloop
Requires-Dist: uvloop ; extra == 'uvloop'
